LICENSE
MANIFEST.in
README.rst
requirements.txt
setup.py
gamma_index/Makefile
gamma_index/__init__.py
gamma_index/gamma.c
gamma_index.egg-info/PKG-INFO
gamma_index.egg-info/SOURCES.txt
gamma_index.egg-info/dependency_links.txt
gamma_index.egg-info/pbr.json
gamma_index.egg-info/requires.txt
gamma_index.egg-info/top_level.txt