Metadata-Version: 1.0
Name: gamma-index
Version: 0.1.3
Summary: gamma_index - calculation of gamma index on multi-dimensional distributions
Home-page: https://github.com/janpipek/gamma_index
Author: Jan Pipek
Author-email: jan.pipek@gmail.com
License: MIT
Platform: UNKNOWN
